llm_clip.py
llm_clip-0.1.dist-info/LICENSE
llm_clip-0.1.dist-info/METADATA
llm_clip-0.1.dist-info/WHEEL
llm_clip-0.1.dist-info/entry_points.txt
llm_clip-0.1.dist-info/top_level.txt
llm_clip-0.1.dist-info/RECORD
