Metadata-Version: 2.1
Name: llm-clip
Version: 0.1
Summary: Generate embeddings for images and text using CLIP with LLM
Author: Simon Willison
License: Apache-2.0
Project-URL: Homepage, https://github.com/simonw/llm-clip
Project-URL: Changelog, https://github.com/simonw/llm-clip/releases
Project-URL: Issues, https://github.com/simonw/llm-clip/issues
Project-URL: CI, https://github.com/simonw/llm-clip/actions
Classifier: License :: OSI Approved :: Apache Software License
License-File: LICENSE
Requires-Dist: llm >=0.10
Requires-Dist: sentence-transformers
Provides-Extra: test
Requires-Dist: pytest ; extra == 'test'
